<?xml version="1.0" encoding="UTF-8" standalone="yes"?>
<localize xmlns:xsi="http://www.w3.org/2001/XMLSchema-instance">
  <text id="day10_angela_1">คุณผู้จัดการคะ? มีอะไรเกิดขึ้นหรือเปล่า?</text>
  <text id="day10_angela_2">อ้อ… เข้าใจแล้วค่ะ</text>
  <text id="day10_angela_3">โปรดรอสักครู่นะคะ ถ้าทนมองไม่ไหว ลองหลับตาลงสักพักเถอะ</text>
  <text id="day10_angela_4">เรียบร้อยค่ะ ฉันแก้ไขแล้ว ปัญหาคือข้อผิดพลาดของระบบ… แปลกจริงๆ ไม่ควรถูกเจาะระบบได้ง่ายๆ แบบนี้เลย</text>
  <text id="day10_angela_5">นี่เป็นเทคโนโลยีที่พัฒนาขึ้นในช่วงสงคราม ก่อนจะถูกนำมาประยุกต์ใช้เชิงพาณิชย์ในภายหลัง</text>
  <text id="day10_angela_6">จริงๆ แล้วก็ไม่ใช่เทคโนโลยีที่ล้ำสมัยอะไรหรอกค่ะ</text>
  <text id="day10_angela_7">สมองของมนุษย์นั้นเปราะบางมาก การได้เห็นภาพที่โหดร้ายและน่าตกใจเกินไป อาจทำให้สมอง “ปิดระบบชั่วคราว” โดยไม่รู้ตัว</text>
  <text id="day10_angela_8">ถ้าผู้จัดการอย่างคุณเกิดภาวะแบบนั้นขึ้นมา มันคงเป็นปัญหาใหญ่สำหรับฉัน</text>
  <text id="day10_angela_9">เพราะแบบนั้น ฉันจึงติดตั้ง "ตัวกรองการรับรู้" ไว้บนหน้าจอของคุณ</text>
  <text id="day10_angela_10">เมื่อระบบตัวกรองทำงาน ศพของพนักงานที่เสียชีวิตจะถูกมองเป็นเพียง ตุ๊กตาน่ารักที่เปื้อนสีแดง</text>
  <text id="day10_angela_11">แม้แต่พวก Abnormality ที่อาจทำลายสภาพจิตใจคุณได้เพียงแค่มอง ก็จะถูกย่อเหลือเป็นเพียงของเล่นน่ารักๆ บนจอภาพในห้องทำงานของคุณ</text>
  <text id="day10_angela_12">เชื่อฉันเถอะค่ะ ก่อนที่ตัวกรองนี้จะถูกติดตั้ง มีผู้จัดการจำนวนมากที่เสียสติไปบนเก้าอี้ตัวนั้น</text>
  <text id="day10_angela_13">ฉันจะไม่มีวันยอมให้คุณเป็นหนึ่งในนั้น</text>
</localize>